[{"univ":"LEI","University":"Leiden University"},{"univ":"UU","University":"University Utrecht"},{"univ":"RUG","University":"University of Groningen"},{"univ":"EUR","University":"Erasmus University Rotterdam"},{"univ":"UM","University":"University Maastricht"},{"univ":"UvA","University":"University of Amsterdam"},{"univ":"VU","University":"Free University of Amsterdam"},{"univ":"RU","University":"Radboud University Nijmegen"},{"univ":"TiU","University":"Tilburg University"},{"univ":"TUD","University":"Delft University of Technology"},{"univ":"TUE","University":"Eindhoven University of Technology"},{"univ":"UT","University":"University of Twente"},{"univ":"WUR","University":"Wageningen University and Research Centre"}]